mdtidy/__init__.py
mdtidy/cleaner.py
mdtidy/combined_processor.py
mdtidy/eval_set.py
mdtidy/gemini_processor.py
mdtidy/gpt_processor.py
mdtidy/policies.py
mdtidy-0.5.2.dist-info/LICENSE
mdtidy-0.5.2.dist-info/METADATA
mdtidy-0.5.2.dist-info/WHEEL
mdtidy-0.5.2.dist-info/top_level.txt
mdtidy-0.5.2.dist-info/RECORD
