Metadata-Version: 2.1
Name: mdtidy
Version: 0.5.2
Summary: A Python library for processing conversation data, creating Jupyter Notebooks, handling Google Drive uploads, and updating Google Sheets.
Home-page: https://github.com/davidkjeremiah/mdtidy
Author: David Jeremiah
Author-email: flasconnect@gmail.com
License: MIT
Classifier: Programming Language :: Python :: 3
Classifier: License :: OSI Approved :: MIT License
Classifier: Operating System :: OS Independent
Requires-Python: >=3.6
License-File: LICENSE
Requires-Dist: requests
Requires-Dist: beautifulsoup4
Requires-Dist: pandas
Requires-Dist: google-api-python-client
Requires-Dist: google-auth-httplib2
Requires-Dist: google-auth-oauthlib
Requires-Dist: gspread
Requires-Dist: oauth2client
Requires-Dist: selenium
Requires-Dist: colorama
